{
  "project": "xiuxian-game",
  "path": "xiuxian-game",
  "functions": [
    {
      "name": "permanentCaveCost",
      "file": "index.html",
      "line": 186
    },
    {
      "name": "getFacilityLevel",
      "file": "index.html",
      "line": 192
    },
    {
      "name": "getPermanentStatBonus",
      "file": "index.html",
      "line": 196
    },
    {
      "name": "savePermanent",
      "file": "index.html",
      "line": 206
    },
    {
      "name": "loadPermanent",
      "file": "index.html",
      "line": 210
    },
    {
      "name": "upgradeCaveFacility",
      "file": "index.html",
      "line": 226
    },
    {
      "name": "getRealmName",
      "file": "index.html",
      "line": 259
    },
    {
      "name": "getRealmRequirement",
      "file": "index.html",
      "line": 265
    },
    {
      "name": "canBreakthrough",
      "file": "index.html",
      "line": 271
    },
    {
      "name": "getBreakthroughRate",
      "file": "index.html",
      "line": 276
    },
    {
      "name": "breakthroughEffect",
      "file": "index.html",
      "line": 284
    },
    {
      "name": "screenFlash",
      "file": "index.html",
      "line": 303
    },
    {
      "name": "screenShake",
      "file": "index.html",
      "line": 310
    },
    {
      "name": "spawnLevelUpRing",
      "file": "index.html",
      "line": 318
    },
    {
      "name": "showEquipNotify",
      "file": "index.html",
      "line": 328
    },
    {
      "name": "addFloatingText",
      "file": "index.html",
      "line": 336
    },
    {
      "name": "spawnParticle",
      "file": "index.html",
      "line": 348
    },
    {
      "name": "drawAttackRange",
      "file": "index.html",
      "line": 360
    },
    {
      "name": "drawSlashArc",
      "file": "index.html",
      "line": 442
    },
    {
      "name": "drawAoeRipples",
      "file": "index.html",
      "line": 474
    },
    {
      "name": "spawnKillExplosion",
      "file": "index.html",
      "line": 494
    },
    {
      "name": "getPlayerAttackRange",
      "file": "index.html",
      "line": 507
    },
    {
      "name": "getPlayerAttackSpeed",
      "file": "index.html",
      "line": 519
    },
    {
      "name": "playerAttack",
      "file": "index.html",
      "line": 531
    },
    {
      "name": "spawnDamageNumber",
      "file": "index.html",
      "line": 608
    },
    {
      "name": "applyDamageToEnemy",
      "file": "index.html",
      "line": 612
    },
    {
      "name": "killEnemy",
      "file": "index.html",
      "line": 632
    },
    {
      "name": "autoEquipItem",
      "file": "index.html",
      "line": 678
    },
    {
      "name": "levelUp",
      "file": "index.html",
      "line": 720
    },
    {
      "name": "generateSPNodes",
      "file": "index.html",
      "line": 772
    },
    {
      "name": "showSPPanel",
      "file": "index.html",
      "line": 779
    },
    {
      "name": "updateSPDisplay",
      "file": "index.html",
      "line": 815
    },
    {
      "name": "generateUpgradeChoices",
      "file": "index.html",
      "line": 821
    },
    {
      "name": "addSkill",
      "file": "index.html",
      "line": 844
    },
    {
      "name": "showUpgradePanel",
      "file": "index.html",
      "line": 855
    },
    {
      "name": "spawnEnemy",
      "file": "index.html",
      "line": 877
    },
    {
      "name": "generateEquip",
      "file": "index.html",
      "line": 936
    },
    {
      "name": "generateRandomEquip",
      "file": "index.html",
      "line": 980
    },
    {
      "name": "useSkill",
      "file": "index.html",
      "line": 1000
    },
    {
      "name": "dist",
      "file": "index.html",
      "line": 1080
    },
    {
      "name": "update",
      "file": "index.html",
      "line": 1085
    },
    {
      "name": "playerDeath",
      "file": "index.html",
      "line": 1290
    },
    {
      "name": "applyPermanentBonuses",
      "file": "index.html",
      "line": 1358
    },
    {
      "name": "fillWithGradient",
      "file": "index.html",
      "line": 1392
    },
    {
      "name": "fillRoundRect",
      "file": "index.html",
      "line": 1400
    },
    {
      "name": "applyScreenShake",
      "file": "index.html",
      "line": 1416
    },
    {
      "name": "triggerScreenShake",
      "file": "index.html",
      "line": 1425
    },
    {
      "name": "drawHexagon",
      "file": "index.html",
      "line": 1431
    },
    {
      "name": "drawTriangle",
      "file": "index.html",
      "line": 1444
    },
    {
      "name": "drawDiamond",
      "file": "index.html",
      "line": 1457
    },
    {
      "name": "drawStar",
      "file": "index.html",
      "line": 1467
    },
    {
      "name": "drawPentagon",
      "file": "index.html",
      "line": 1481
    },
    {
      "name": "render",
      "file": "index.html",
      "line": 1494
    },
    {
      "name": "lightenColor",
      "file": "index.html",
      "line": 2070
    },
    {
      "name": "updateHUD",
      "file": "index.html",
      "line": 2086
    },
    {
      "name": "updateSkillBar",
      "file": "index.html",
      "line": 2101
    },
    {
      "name": "updateEquipBar",
      "file": "index.html",
      "line": 2123
    },
    {
      "name": "updateInventoryPanel",
      "file": "index.html",
      "line": 2146
    },
    {
      "name": "equipItem",
      "file": "index.html",
      "line": 2204
    },
    {
      "name": "unequipItem",
      "file": "index.html",
      "line": 2231
    },
    {
      "name": "recalcStats",
      "file": "index.html",
      "line": 2240
    },
    {
      "name": "showTooltip",
      "file": "index.html",
      "line": 2269
    },
    {
      "name": "hideTooltip",
      "file": "index.html",
      "line": 2279
    },
    {
      "name": "positionTooltip",
      "file": "index.html",
      "line": 2281
    },
    {
      "name": "showCavePanel",
      "file": "index.html",
      "line": 2291
    },
    {
      "name": "renderCaveUpgradeList",
      "file": "index.html",
      "line": 2304
    },
    {
      "name": "showBreakthroughPanel",
      "file": "index.html",
      "line": 2357
    },
    {
      "name": "saveGame",
      "file": "index.html",
      "line": 2398
    },
    {
      "name": "loadGame",
      "file": "index.html",
      "line": 2414
    },
    {
      "name": "init",
      "file": "index.html",
      "line": 2444
    },
    {
      "name": "gameLoop",
      "file": "index.html",
      "line": 2526
    },
    {
      "name": "randomColor",
      "file": "index.html",
      "line": 2544
    },
    {
      "name": "log",
      "file": "tests/test-upgrade.html",
      "line": 4
    },
    {
      "name": "clearLog",
      "file": "tests/test-upgrade.html",
      "line": 10
    },
    {
      "name": "testLevelUpChain",
      "file": "tests/test-upgrade.html",
      "line": 22
    },
    {
      "name": "testSpawnLevelUpRing",
      "file": "tests/test-upgrade.html",
      "line": 74
    },
    {
      "name": "testScreenFlash",
      "file": "tests/test-upgrade.html",
      "line": 110
    }
  ],
  "elements": [
    {
      "name": "gameCanvas",
      "file": "index.html",
      "line": 266
    },
    {
      "name": "hud",
      "file": "index.html",
      "line": 269
    },
    {
      "name": "tooltip",
      "file": "index.html",
      "line": 306
    },
    {
      "name": "log",
      "file": "tests/test-upgrade.html",
      "line": 27
    }
  ],
  "configs": [
    {
      "name": "CAVE_FACILITIES",
      "file": "index.html",
      "line": 110
    },
    {
      "name": "LIBRARY_SKILL_POOL",
      "file": "index.html",
      "line": 149
    },
    {
      "name": "ARMORY_WEAPON_POOL",
      "file": "index.html",
      "line": 157
    },
    {
      "name": "SP_NODE_POOL",
      "file": "index.html",
      "line": 747
    }
  ],
  "classes": [],
  "raw": [
    {
      "type": "element",
      "name": "gameCanvas",
      "line": 266,
      "file": "index.html"
    },
    {
      "type": "element",
      "name": "hud",
      "line": 269,
      "file": "index.html"
    },
    {
      "type": "element",
      "name": "tooltip",
      "line": 306,
      "file": "index.html"
    },
    {
      "type": "config",
      "name": "CAVE_FACILITIES",
      "line": 110,
      "file": "index.html"
    },
    {
      "type": "config",
      "name": "LIBRARY_SKILL_POOL",
      "line": 149,
      "file": "index.html"
    },
    {
      "type": "config",
      "name": "ARMORY_WEAPON_POOL",
      "line": 157,
      "file": "index.html"
    },
    {
      "type": "function",
      "name": "permanentCaveCost",
      "line": 186,
      "file": "index.html"
    },
    {
      "type": "function",
      "name": "getFacilityLevel",
      "line": 192,
      "file": "index.html"
    },
    {
      "type": "function",
      "name": "getPermanentStatBonus",
      "line": 196,
      "file": "index.html"
    },
    {
      "type": "function",
      "name": "savePermanent",
      "line": 206,
      "file": "index.html"
    },
    {
      "type": "function",
      "name": "loadPermanent",
      "line": 210,
      "file": "index.html"
    },
    {
      "type": "function",
      "name": "upgradeCaveFacility",
      "line": 226,
      "file": "index.html"
    },
    {
      "type": "function",
      "name": "getRealmName",
      "line": 259,
      "file": "index.html"
    },
    {
      "type": "function",
      "name": "getRealmRequirement",
      "line": 265,
      "file": "index.html"
    },
    {
      "type": "function",
      "name": "canBreakthrough",
      "line": 271,
      "file": "index.html"
    },
    {
      "type": "function",
      "name": "getBreakthroughRate",
      "line": 276,
      "file": "index.html"
    },
    {
      "type": "function",
      "name": "breakthroughEffect",
      "line": 284,
      "file": "index.html"
    },
    {
      "type": "function",
      "name": "screenFlash",
      "line": 303,
      "file": "index.html"
    },
    {
      "type": "function",
      "name": "screenShake",
      "line": 310,
      "file": "index.html"
    },
    {
      "type": "function",
      "name": "spawnLevelUpRing",
      "line": 318,
      "file": "index.html"
    },
    {
      "type": "function",
      "name": "showEquipNotify",
      "line": 328,
      "file": "index.html"
    },
    {
      "type": "function",
      "name": "addFloatingText",
      "line": 336,
      "file": "index.html"
    },
    {
      "type": "function",
      "name": "spawnParticle",
      "line": 348,
      "file": "index.html"
    },
    {
      "type": "function",
      "name": "drawAttackRange",
      "line": 360,
      "file": "index.html"
    },
    {
      "type": "function",
      "name": "drawSlashArc",
      "line": 442,
      "file": "index.html"
    },
    {
      "type": "function",
      "name": "drawAoeRipples",
      "line": 474,
      "file": "index.html"
    },
    {
      "type": "function",
      "name": "spawnKillExplosion",
      "line": 494,
      "file": "index.html"
    },
    {
      "type": "function",
      "name": "getPlayerAttackRange",
      "line": 507,
      "file": "index.html"
    },
    {
      "type": "function",
      "name": "getPlayerAttackSpeed",
      "line": 519,
      "file": "index.html"
    },
    {
      "type": "function",
      "name": "playerAttack",
      "line": 531,
      "file": "index.html"
    },
    {
      "type": "function",
      "name": "spawnDamageNumber",
      "line": 608,
      "file": "index.html"
    },
    {
      "type": "function",
      "name": "applyDamageToEnemy",
      "line": 612,
      "file": "index.html"
    },
    {
      "type": "function",
      "name": "killEnemy",
      "line": 632,
      "file": "index.html"
    },
    {
      "type": "function",
      "name": "autoEquipItem",
      "line": 678,
      "file": "index.html"
    },
    {
      "type": "function",
      "name": "levelUp",
      "line": 720,
      "file": "index.html"
    },
    {
      "type": "config",
      "name": "SP_NODE_POOL",
      "line": 747,
      "file": "index.html"
    },
    {
      "type": "function",
      "name": "generateSPNodes",
      "line": 772,
      "file": "index.html"
    },
    {
      "type": "function",
      "name": "showSPPanel",
      "line": 779,
      "file": "index.html"
    },
    {
      "type": "function",
      "name": "updateSPDisplay",
      "line": 815,
      "file": "index.html"
    },
    {
      "type": "function",
      "name": "generateUpgradeChoices",
      "line": 821,
      "file": "index.html"
    },
    {
      "type": "function",
      "name": "addSkill",
      "line": 844,
      "file": "index.html"
    },
    {
      "type": "function",
      "name": "showUpgradePanel",
      "line": 855,
      "file": "index.html"
    },
    {
      "type": "function",
      "name": "spawnEnemy",
      "line": 877,
      "file": "index.html"
    },
    {
      "type": "function",
      "name": "generateEquip",
      "line": 936,
      "file": "index.html"
    },
    {
      "type": "function",
      "name": "generateRandomEquip",
      "line": 980,
      "file": "index.html"
    },
    {
      "type": "function",
      "name": "useSkill",
      "line": 1000,
      "file": "index.html"
    },
    {
      "type": "function",
      "name": "dist",
      "line": 1080,
      "file": "index.html"
    },
    {
      "type": "function",
      "name": "update",
      "line": 1085,
      "file": "index.html"
    },
    {
      "type": "function",
      "name": "playerDeath",
      "line": 1290,
      "file": "index.html"
    },
    {
      "type": "function",
      "name": "applyPermanentBonuses",
      "line": 1358,
      "file": "index.html"
    },
    {
      "type": "function",
      "name": "fillWithGradient",
      "line": 1392,
      "file": "index.html"
    },
    {
      "type": "function",
      "name": "fillRoundRect",
      "line": 1400,
      "file": "index.html"
    },
    {
      "type": "function",
      "name": "applyScreenShake",
      "line": 1416,
      "file": "index.html"
    },
    {
      "type": "function",
      "name": "triggerScreenShake",
      "line": 1425,
      "file": "index.html"
    },
    {
      "type": "function",
      "name": "drawHexagon",
      "line": 1431,
      "file": "index.html"
    },
    {
      "type": "function",
      "name": "drawTriangle",
      "line": 1444,
      "file": "index.html"
    },
    {
      "type": "function",
      "name": "drawDiamond",
      "line": 1457,
      "file": "index.html"
    },
    {
      "type": "function",
      "name": "drawStar",
      "line": 1467,
      "file": "index.html"
    },
    {
      "type": "function",
      "name": "drawPentagon",
      "line": 1481,
      "file": "index.html"
    },
    {
      "type": "function",
      "name": "render",
      "line": 1494,
      "file": "index.html"
    },
    {
      "type": "function",
      "name": "lightenColor",
      "line": 2070,
      "file": "index.html"
    },
    {
      "type": "function",
      "name": "updateHUD",
      "line": 2086,
      "file": "index.html"
    },
    {
      "type": "function",
      "name": "updateSkillBar",
      "line": 2101,
      "file": "index.html"
    },
    {
      "type": "function",
      "name": "updateEquipBar",
      "line": 2123,
      "file": "index.html"
    },
    {
      "type": "function",
      "name": "updateInventoryPanel",
      "line": 2146,
      "file": "index.html"
    },
    {
      "type": "function",
      "name": "equipItem",
      "line": 2204,
      "file": "index.html"
    },
    {
      "type": "function",
      "name": "unequipItem",
      "line": 2231,
      "file": "index.html"
    },
    {
      "type": "function",
      "name": "recalcStats",
      "line": 2240,
      "file": "index.html"
    },
    {
      "type": "function",
      "name": "showTooltip",
      "line": 2269,
      "file": "index.html"
    },
    {
      "type": "function",
      "name": "hideTooltip",
      "line": 2279,
      "file": "index.html"
    },
    {
      "type": "function",
      "name": "positionTooltip",
      "line": 2281,
      "file": "index.html"
    },
    {
      "type": "function",
      "name": "showCavePanel",
      "line": 2291,
      "file": "index.html"
    },
    {
      "type": "function",
      "name": "renderCaveUpgradeList",
      "line": 2304,
      "file": "index.html"
    },
    {
      "type": "function",
      "name": "showBreakthroughPanel",
      "line": 2357,
      "file": "index.html"
    },
    {
      "type": "function",
      "name": "saveGame",
      "line": 2398,
      "file": "index.html"
    },
    {
      "type": "function",
      "name": "loadGame",
      "line": 2414,
      "file": "index.html"
    },
    {
      "type": "function",
      "name": "init",
      "line": 2444,
      "file": "index.html"
    },
    {
      "type": "function",
      "name": "gameLoop",
      "line": 2526,
      "file": "index.html"
    },
    {
      "type": "function",
      "name": "randomColor",
      "line": 2544,
      "file": "index.html"
    },
    {
      "type": "element",
      "name": "log",
      "line": 27,
      "file": "tests/test-upgrade.html"
    },
    {
      "type": "function",
      "name": "log",
      "line": 4,
      "file": "tests/test-upgrade.html"
    },
    {
      "type": "function",
      "name": "clearLog",
      "line": 10,
      "file": "tests/test-upgrade.html"
    },
    {
      "type": "function",
      "name": "testLevelUpChain",
      "line": 22,
      "file": "tests/test-upgrade.html"
    },
    {
      "type": "function",
      "name": "testSpawnLevelUpRing",
      "line": 74,
      "file": "tests/test-upgrade.html"
    },
    {
      "type": "function",
      "name": "testScreenFlash",
      "line": 110,
      "file": "tests/test-upgrade.html"
    }
  ],
  "updatedAt": "2026-05-07T08:42:41+08:00"
}